ulmtools/__init__.py
ulmtools/ulmtools.abi3.so
ulmtools-0.1.1.dist-info/METADATA
ulmtools-0.1.1.dist-info/WHEEL
ulmtools-0.1.1.dist-info/RECORD
