Metadata-Version: 2.4
Name: ulmtools
Version: 0.1.1
Classifier: Programming Language :: Rust
Classifier: Programming Language :: Python :: Implementation :: CPython
Classifier: Programming Language :: Python :: Implementation :: PyPy
Requires-Dist: numpy>=2.0,!=2.4.0
Summary: A collection of tools for ultrasound localization microscopy (ULM).
Requires-Python: >=3.8
